attr.py
dry_attr.py
attr-0.3.0.dist-info/DESCRIPTION.rst
attr-0.3.0.dist-info/METADATA
attr-0.3.0.dist-info/RECORD
attr-0.3.0.dist-info/WHEEL
attr-0.3.0.dist-info/metadata.json
attr-0.3.0.dist-info/top_level.txt
