Metadata-Version: 2.0
Name: attr
Version: 0.3.0
Summary: Simple decorator to set attributes of target function or class in a DRY way.
Home-page: https://github.com/denis-ryzhkov/attr
Author: Denis Ryzhkov
Author-email: denisr@denisr.com
License: MIT
Platform: UNKNOWN
Classifier: Development Status :: 4 - Beta
Classifier: License :: OSI Approved :: MIT License
Classifier: Operating System :: OS Independent
Classifier: Programming Language :: Python :: 2.7
Classifier: Programming Language :: Python :: 3
Classifier: Topic :: Software Development :: Libraries :: Python Modules
